{"cameraMode":{"drawMode":0,"name":"Shaded","section":"Shading Mode"},"sceneLighting":false,"audioPlay":false,"sceneViewState":{"m_AlwaysRefresh":false,"showFog":true,"showSkybox":false,"showFlares":true,"showImageEffects":true,"showParticleSystems":true,"showVisualEffectGraphs":true,"m_FxEnabled":true},"in2DMode":false,"pivot":{"x":21.22087860107422,"y":-1.1137113571166993,"z":0.38764452934265139},"rotation":{"x":-0.34290021657943728,"y":-0.38696470856666567,"z":0.1577145755290985,"w":-0.8413395881652832},"size":2.634161949157715,"orthographic":false}